msgraph/__init__.py
msgraph/core.py
msgraph/devices.py
msgraph/groups.py
msgraph/identity.py
msgraph/mail.py
msgraph_py-1.4.1.dist-info/LICENSE
msgraph_py-1.4.1.dist-info/METADATA
msgraph_py-1.4.1.dist-info/WHEEL
msgraph_py-1.4.1.dist-info/top_level.txt
msgraph_py-1.4.1.dist-info/RECORD
