Metadata-Version: 2.2
Name: msgraph-py
Version: 1.4.1
Summary: This package contains API wrappers to simplify interaction with Microsoft Graph API through Python functions.
Author: fedamerd
License: MIT License
Project-URL: Changelog, https://github.com/fedamerd/msgraph-py/blob/main/CHANGELOG.md
Project-URL: Documentation, https://github.com/fedamerd/msgraph-py/blob/main/README.md
Project-URL: Issues, https://github.com/fedamerd/msgraph-py/issues
Project-URL: Source, https://github.com/fedamerd/msgraph-py
Classifier: Programming Language :: Python :: 3.9
Classifier: License :: OSI Approved :: MIT License
Classifier: Operating System :: OS Independent
Requires-Python: >=3.9
License-File: LICENSE
Requires-Dist: httpx[http2]
Requires-Dist: PyJWT[crypto]
